iplot/__init__.py
iplot/examples/__init__.py
iplot/examples/baraglut.py
iplot/examples/boxplot.py
iplot/examples/cascata.py
iplot/examples/intercambios.py
iplot/examples/plot.py
iplot/examples/plotRapido.py
iplot/examples/sin.py
iplot/examples/submercado.py
iplot/examples/usina.py
iplot/layout/Layout_Plot_Diff.py
iplot/layout/Layout_Plot_Personalizado.py
iplot/layout/Layout_Plot_Simples.py
iplot/layout/__init__.py
iplot/modelo/EstruturasGerais.py
iplot/modelo/Newave.py
iplot/modelo/SADHI.py
iplot/modelo/SDDP.py
iplot/modelo/__init__.py
iplot/modelo/source_Newave/Newave_Armazenamento.py
iplot/modelo/source_Newave/Newave_CMO.py
iplot/modelo/source_Newave/Newave_Convergencia.py
iplot/modelo/source_Newave/Newave_Energia.py
iplot/modelo/source_Newave/Newave_Estruturadores.py
iplot/modelo/source_Newave/Newave_Geracao.py
iplot/modelo/source_Newave/Newave_Vazao.py
iplot/modelo/source_Newave/Newave_Volume.py
iplot/modelo/source_Newave/__init__.py
iplot/modelo/source_SDDP/SDDP_Armazenamento.py
iplot/modelo/source_SDDP/SDDP_CMO.py
iplot/modelo/source_SDDP/SDDP_Convergencia.py
iplot/modelo/source_SDDP/SDDP_Energia.py
iplot/modelo/source_SDDP/SDDP_Geracao.py
iplot/modelo/source_SDDP/SDDP_Vazao.py
iplot/modelo/source_SDDP/SDDP_Volume.py
iplot/modelo/source_SDDP/__init__.py
iplot/source/__init__.py
iplot/source/figure.py
iplot/source/frame.py
iplot/source/gerenciadorArquivos.py
iplot/source/interpretador.py
iplot/source/iplot.py
iplot/source/case/__init__.py
iplot/source/case/armazenamento.py
iplot/source/case/cmo.py
iplot/source/case/convergencia.py
iplot/source/case/energia.py
iplot/source/case/geracao.py
iplot/source/case/intercambio.py
iplot/source/case/vazao.py
iplot/source/case/volume.py
iplot/source/go/__init__.py
iplot/source/go/dadoEixo.py
iplot/source/go/goGrafico.py
plotador-5.0.15.dist-info/LICENSE
plotador-5.0.15.dist-info/METADATA
plotador-5.0.15.dist-info/WHEEL
plotador-5.0.15.dist-info/top_level.txt
plotador-5.0.15.dist-info/RECORD
